BayesCCal/BayesCCal.py
BayesCCal/__init__.py
BayesCCal-0.1.1.dist-info/LICENSE
BayesCCal-0.1.1.dist-info/METADATA
BayesCCal-0.1.1.dist-info/WHEEL
BayesCCal-0.1.1.dist-info/top_level.txt
BayesCCal-0.1.1.dist-info/RECORD
