Metadata-Version: 2.1
Name: BayesCCal
Version: 0.1.1
Summary: Bayesian calibration of classifiers
Author: Marco Puts
Author-email: mputs@acm.org
License-File: LICENSE
Requires-Dist: numpy
Requires-Dist: scipy
